sqlalchemy_extras/__init__.py
sqlalchemy_extras/fastapi.py
sqlalchemy_extras/models.py
sqlalchemy_extras/py.typed
sqlalchemy_extras/utils.py
sqlalchemy_extras-2.0.5.dist-info/METADATA
sqlalchemy_extras-2.0.5.dist-info/WHEEL
sqlalchemy_extras-2.0.5.dist-info/RECORD
